04_iverilog_gtkwave_counter/code.v
// Example of binary_counter
module binary_counter
   #(parameter N=4)
   (
    input wire clk, reset,
    output wire [N-1:0] binary
   );
 
   reg [N-1:0] r_reg;
   wire [N-1:0] r_next;
 
   always @(posedge clk, negedge reset)
   begin
      if (~reset)
         r_reg <= 0;
      else
         r_reg <= r_next;
	end	
	assign binary  = r_reg;
	assign r_next = r_reg + 2;
endmodule

04_iverilog_gtkwave_counter/code_tb.v
`timescale 1ns / 1ps
module stimulus;
	// Inputs
	reg clk ;
	reg reset;
	// Output
	wire [3:0] binary;
	// Instantiate the Binary Counter
	binary_counter  #(4) s1  (
		.clk(clk), 
		.reset(reset),
		.binary(binary)
	);
 
 integer i;
 
initial 
begin

$dumpfile("out_test.vcd");
$dumpvars(0,stimulus);
$monitor("clk=%d binary=%4b",clk,binary);

 clk = 0;

 
reset = 1;
#2 reset = 0;
#2 reset = 1;

 for(i =0; i<=30; i=i+1)
  #50 clk = ~clk;
end
 
 
		initial begin
//		 $monitor("clk=%d binary=%4b",clk,binary);
		 end
 
endmodule

04_iverilog_gtkwave_counter/out_test.vcd
$date
	Fri Nov 01 22:53:44 2019
$end
$version
	Icarus Verilog
$end
$timescale
	1ps
$end
$scope module stimulus $end
$var wire 4 ! binary [3:0] $end
$var reg 1 " clk $end
$var reg 1 # reset $end
$var integer 32 $ i [31:0] $end
$scope module s1 $end
$var wire 4 % binary [3:0] $end
$var wire 1 " clk $end
$var wire 1 # reset $end
$var wire 4 & r_next [3:0] $end
$var reg 4 ' r_reg [3:0] $end
$upscope $end
$upscope $end
$enddefinitions $end
#0
$dumpvars
bx '
bx &
bx %
bx $
1#
0"
bx !
$end
#2000
b10 &
b0 !
b0 %
b0 '
0#
#4000
b0 $
1#
#54000
b100 &
b10 !
b10 %
b10 '
b1 $
1"
#104000
b10 $
0"
#154000
b110 &
b100 !
b100 %
b100 '
b11 $
1"
#204000
b100 $
0"
#254000
b1000 &
b110 !
b110 %
b110 '
b101 $
1"
#304000
b110 $
0"
#354000
b1010 &
b1000 !
b1000 %
b1000 '
b111 $
1"
#404000
b1000 $
0"
#454000
b1100 &
b1010 !
b1010 %
b1010 '
b1001 $
1"
#504000
b1010 $
0"
#554000
b1110 &
b1100 !
b1100 %
b1100 '
b1011 $
1"
#604000
b1100 $
0"
#654000
b0 &
b1110 !
b1110 %
b1110 '
b1101 $
1"
#704000
b1110 $
0"
#754000
b10 &
b0 !
b0 %
b0 '
b1111 $
1"
#804000
b10000 $
0"
#854000
b100 &
b10 !
b10 %
b10 '
b10001 $
1"
#904000
b10010 $
0"
#954000
b110 &
b100 !
b100 %
b100 '
b10011 $
1"
#1004000
b10100 $
0"
#1054000
b1000 &
b110 !
b110 %
b110 '
b10101 $
1"
#1104000
b10110 $
0"
#1154000
b1010 &
b1000 !
b1000 %
b1000 '
b10111 $
1"
#1204000
b11000 $
0"
#1254000
b1100 &
b1010 !
b1010 %
b1010 '
b11001 $
1"
#1304000
b11010 $
0"
#1354000
b1110 &
b1100 !
b1100 %
b1100 '
b11011 $
1"
#1404000
b11100 $
0"
#1454000
b0 &
b1110 !
b1110 %
b1110 '
b11101 $
1"
#1504000
b11110 $
0"
#1554000
b10 &
b0 !
b0 %
b0 '
b11111 $
1"
