04_iverilog_gtkwave_counter/code.v
// Example of binary_counter
module binary_counter
   #(parameter N=4)
   (
    input wire clk, reset,
    output wire [N-1:0] binary
   );
 
   reg [N-1:0] r_reg;
   wire [N-1:0] r_next;
 
   always @(posedge clk, negedge reset)
   begin
      if (~reset)
         r_reg <= 0;
      else
         r_reg <= r_next;
	end	
	assign binary  = r_reg;
	assign r_next = r_reg + 1;
endmodule

04_iverilog_gtkwave_counter/code_tb.v
`timescale 1ns / 1ps
module stimulus;
	// Inputs
	reg clk ;
	reg reset;
	// Output
	wire [3:0] binary;
	// Instantiate the Binary Counter
	binary_counter  #(4) s1  (
		.clk(clk), 
		.reset(reset),
		.binary(binary)
	);
 
 integer i;
 initial 
 begin
 /*
 clk = 0;
 for(i =0; i<=40; i=i+1)
 begin
  #10 clk = ~clk;
 end*/
 end
 
initial 
begin

$dumpfile("out_test.vcd");
$dumpvars(0,stimulus);

 clk = 0;

 
reset = 1;
#2 reset = 0;
#2 reset = 1;

 for(i =0; i<=30; i=i+1)
  #10 clk = ~clk;
end
 
 
		initial begin
		 $monitor("clk=%d binary=%4b",clk,binary);
		 end
 
endmodule

04_iverilog_gtkwave_counter/out_test.vcd
$date
	Thu Oct 31 15:17:11 2019
$end
$version
	Icarus Verilog
$end
$timescale
	1ps
$end
$scope module stimulus $end
$var wire 4 ! binary [3:0] $end
$var reg 1 " clk $end
$var reg 1 # reset $end
$var integer 32 $ i [31:0] $end
$scope module s1 $end
$var wire 4 % binary [3:0] $end
$var wire 1 " clk $end
$var wire 1 # reset $end
$var wire 4 & r_next [3:0] $end
$var reg 4 ' r_reg [3:0] $end
$upscope $end
$upscope $end
$enddefinitions $end
#0
$dumpvars
bx '
bx &
bx %
bx $
1#
0"
bx !
$end
#2000
b1 &
b0 !
b0 %
b0 '
0#
#4000
b0 $
1#
#14000
b10 &
b1 !
b1 %
b1 '
b1 $
1"
#24000
b10 $
0"
#34000
b11 &
b10 !
b10 %
b10 '
b11 $
1"
#44000
b100 $
0"
#54000
b100 &
b11 !
b11 %
b11 '
b101 $
1"
#64000
b110 $
0"
#74000
b101 &
b100 !
b100 %
b100 '
b111 $
1"
#84000
b1000 $
0"
#94000
b110 &
b101 !
b101 %
b101 '
b1001 $
1"
#104000
b1010 $
0"
#114000
b111 &
b110 !
b110 %
b110 '
b1011 $
1"
#124000
b1100 $
0"
#134000
b1000 &
b111 !
b111 %
b111 '
b1101 $
1"
#144000
b1110 $
0"
#154000
b1001 &
b1000 !
b1000 %
b1000 '
b1111 $
1"
#164000
b10000 $
0"
#174000
b1010 &
b1001 !
b1001 %
b1001 '
b10001 $
1"
#184000
b10010 $
0"
#194000
b1011 &
b1010 !
b1010 %
b1010 '
b10011 $
1"
#204000
b10100 $
0"
#214000
b1100 &
b1011 !
b1011 %
b1011 '
b10101 $
1"
#224000
b10110 $
0"
#234000
b1101 &
b1100 !
b1100 %
b1100 '
b10111 $
1"
#244000
b11000 $
0"
#254000
b1110 &
b1101 !
b1101 %
b1101 '
b11001 $
1"
#264000
b11010 $
0"
#274000
b1111 &
b1110 !
b1110 %
b1110 '
b11011 $
1"
#284000
b11100 $
0"
#294000
b0 &
b1111 !
b1111 %
b1111 '
b11101 $
1"
#304000
b11110 $
0"
#314000
b1 &
b0 !
b0 %
b0 '
b11111 $
1"
